phasma/__init__.py
phasma/__main__.py
phasma/browser.py
phasma/phasma.py
phasma/driver/__init__.py
phasma/driver/download.py
phasma/driver/driver.py
phasma/driver/phantomjs/ChangeLog
phasma/driver/phantomjs/LICENSE.BSD
phasma/driver/phantomjs/README.md
phasma/driver/phantomjs/third-party.txt
phasma/driver/phantomjs/bin/phantomjs
phasma/driver/phantomjs/examples/arguments.js
phasma/driver/phantomjs/examples/child_process-examples.js
phasma/driver/phantomjs/examples/colorwheel.js
phasma/driver/phantomjs/examples/countdown.js
phasma/driver/phantomjs/examples/detectsniff.js
phasma/driver/phantomjs/examples/echoToFile.js
phasma/driver/phantomjs/examples/features.js
phasma/driver/phantomjs/examples/fibo.js
phasma/driver/phantomjs/examples/hello.js
phasma/driver/phantomjs/examples/injectme.js
phasma/driver/phantomjs/examples/loadspeed.js
phasma/driver/phantomjs/examples/loadurlwithoutcss.js
phasma/driver/phantomjs/examples/modernizr.js
phasma/driver/phantomjs/examples/module.js
phasma/driver/phantomjs/examples/netlog.js
phasma/driver/phantomjs/examples/netsniff.js
phasma/driver/phantomjs/examples/openurlwithproxy.js
phasma/driver/phantomjs/examples/outputEncoding.js
phasma/driver/phantomjs/examples/page_events.js
phasma/driver/phantomjs/examples/pagecallback.js
phasma/driver/phantomjs/examples/phantomwebintro.js
phasma/driver/phantomjs/examples/post.js
phasma/driver/phantomjs/examples/postjson.js
phasma/driver/phantomjs/examples/postserver.js
phasma/driver/phantomjs/examples/printenv.js
phasma/driver/phantomjs/examples/printheaderfooter.js
phasma/driver/phantomjs/examples/printmargins.js
phasma/driver/phantomjs/examples/rasterize.js
phasma/driver/phantomjs/examples/render_multi_url.js
phasma/driver/phantomjs/examples/responsive-screenshot.js
phasma/driver/phantomjs/examples/run-jasmine.js
phasma/driver/phantomjs/examples/run-jasmine2.js
phasma/driver/phantomjs/examples/run-qunit.js
phasma/driver/phantomjs/examples/scandir.js
phasma/driver/phantomjs/examples/server.js
phasma-0.5.0.dist-info/licenses/LICENSE
phasma-0.5.0.dist-info/METADATA
phasma-0.5.0.dist-info/WHEEL
phasma-0.5.0.dist-info/top_level.txt
phasma-0.5.0.dist-info/RECORD
