Metadata-Version: 2.4
Name: phasma
Version: 0.5.0
Summary: A modern PhantomJS driver for Python with bundled binaries, providing headless browser automation, web page rendering, and JavaScript execution.
Author-email: Mohammad Raziei <mohammadraziei1375@gmail.com>
License: MIT License
Project-URL: Source, https://github.com/mohammadraziei/phasma
Project-URL: Issues, https://github.com/mohammadraziei/phasma/issues
Project-URL: Documentation, https://mohammadraziei.github.io/phasma
Keywords: phantomjs,headless-browser,web-automation,javascript,web-scraping
Platform: Linux
Platform: Windows
Platform: macOS
Classifier: Development Status :: 4 - Beta
Classifier: Operating System :: OS Independent
Classifier: Programming Language :: Python :: 3
Classifier: Operating System :: POSIX :: Linux
Classifier: Operating System :: MacOS :: MacOS X
Classifier: Operating System :: Microsoft :: Windows
Classifier: Topic :: Internet :: WWW/HTTP :: Browsers
Classifier: Topic :: Software Development :: Testing
Classifier: Topic :: Software Development :: Libraries :: Python Modules
Requires-Python: >=3.4
License-File: LICENSE
Provides-Extra: dev
Requires-Dist: pytest-asyncio>=0.21.0; extra == "dev"
Dynamic: license-file
Dynamic: platform
